shinigami.py
shinigami-0.2.1.dist-info/LICENSE
shinigami-0.2.1.dist-info/METADATA
shinigami-0.2.1.dist-info/WHEEL
shinigami-0.2.1.dist-info/entry_points.txt
shinigami-0.2.1.dist-info/top_level.txt
shinigami-0.2.1.dist-info/RECORD
