Metadata-Version: 2.1
Name: shinigami
Version: 0.2.1
Summary: Shinigami is an open source Python library allowing the user to generate and build Dockerfiles during runtime
Home-page: https://github.com/battleoverflow/shinigami
Author: battleoverflow
Classifier: Programming Language :: Python :: 3
Classifier: License :: OSI Approved :: BSD License
Classifier: Operating System :: OS Independent
Requires-Python: >=3.6
License-File: LICENSE
Requires-Dist: argparse
Requires-Dist: faye
